bfi_toolkit/__init__.py
bfi_toolkit/baseflow.py
bfi_toolkit/convert.py
bfi_toolkit/core.py
bfi_toolkit/optimization.py
bfi_toolkit/plotting.py
bfi_toolkit/utils/__init__.py
bfi_toolkit/utils/data_utils.py
bfi_toolkit/utils/logger.py
bfi_toolkit/utils/validation.py
bfi_toolkit-0.1.3.dist-info/licenses/LICENSE
bfi_toolkit-0.1.3.dist-info/METADATA
bfi_toolkit-0.1.3.dist-info/WHEEL
bfi_toolkit-0.1.3.dist-info/top_level.txt
bfi_toolkit-0.1.3.dist-info/RECORD
