Metadata-Version: 2.4
Name: bfi_toolkit
Version: 0.1.3
Summary: A simple toolkit for baseflow separation and Baseflow Index (BFI) estimation from daily streamflow.
Author: Mohammad Ali Farmani
License: MIT
Project-URL: Homepage, https://github.com/mfarmani95/BFI-Toolkit
Project-URL: Source, https://github.com/mfarmani95/BFI-Toolkit
Project-URL: Issue Tracker, https://github.com/mfarmani95/BFI-Toolkit/issues
Keywords: hydrology,baseflow,BFI,streamflow,recession
Classifier: Intended Audience :: Science/Research
Classifier: License :: OSI Approved :: MIT License
Classifier: Programming Language :: Python :: 3
Classifier: Topic :: Scientific/Engineering :: Hydrology
Requires-Python: >=3.9
License-File: LICENSE
Requires-Dist: numpy
Requires-Dist: pandas
Requires-Dist: scipy
Requires-Dist: matplotlib
Dynamic: license-file
